venomx/__init__.py
venomx/model/embedding.yaml
venomx/model/embeddings_pa.py
venomx/model/venomx.py
venomx/model/venomx.yaml
venomx/tools/__init__.py
venomx/tools/cli.py
venomx/tools/file_io.py
venomx-0.1.1.dist-info/LICENSE
venomx-0.1.1.dist-info/METADATA
venomx-0.1.1.dist-info/WHEEL
venomx-0.1.1.dist-info/entry_points.txt
venomx-0.1.1.dist-info/RECORD
