Metadata-Version: 2.1
Name: venomx
Version: 0.1.1
Summary: venomx
License: BSD-3
Author: Author 1
Author-email: author@org.org
Requires-Python: >=3.9,<4.0
Classifier: License :: Other/Proprietary License
Classifier: Programming Language :: Python :: 3
Classifier: Programming Language :: Python :: 3.9
Classifier: Programming Language :: Python :: 3.10
Classifier: Programming Language :: Python :: 3.11
Classifier: Programming Language :: Python :: 3.12
Requires-Dist: click
Requires-Dist: importlib-metadata (>=4.8.0)
Requires-Dist: pandas (>=2.2.0,<3.0.0)
Requires-Dist: pyarrow (>=15.0.0,<16.0.0)
